dagster_contrib_anthropic/__init__.py
dagster_contrib_anthropic/resource.py
dagster_contrib_anthropic-0.0.1.dist-info/METADATA
dagster_contrib_anthropic-0.0.1.dist-info/WHEEL
dagster_contrib_anthropic-0.0.1.dist-info/top_level.txt
dagster_contrib_anthropic-0.0.1.dist-info/RECORD
