Metadata-Version: 2.2
Name: dagster-contrib-anthropic
Version: 0.0.1
Summary: Dagster integration with Anthropic
Requires-Python: >=3.9
Requires-Dist: dagster>=1.8.0
Requires-Dist: anthropic>=0.42.0
